[
  {
    "id": "6",
    "name": "Saida Del Valle Brito"
  },
  {
    "id": "9",
    "name": "Adonai Luque"
  },
  {
    "id": "10",
    "name": "Albert Castellano"
  },
  {
    "id": "11",
    "name": "Alessandro Chumpitaz"
  },
  {
    "id": "12",
    "name": "Alexander Chavarria"
  },
  {
    "id": "13",
    "name": "Rai Delgado"
  },
  {
    "id": "14",
    "name": "Benjamin Maguiña"
  },
  {
    "id": "15",
    "name": "Elvis Quispe"
  },
  {
    "id": "16",
    "name": "Erick Saavedra"
  },
  {
    "id": "17",
    "name": "Fernando Pareja"
  },
  {
    "id": "18",
    "name": "Joel Eche"
  },
  {
    "id": "19",
    "name": "Freddy Munive"
  },
  {
    "id": "20",
    "name": "Gerard Altamirano"
  },
  {
    "id": "21",
    "name": "Gustavo Panebra"
  },
  {
    "id": "22",
    "name": "Joaquín Meza"
  },
  {
    "id": "23",
    "name": "Jorge Luis Alayo"
  },
  {
    "id": "24",
    "name": "Jorge Gonzales"
  },
  {
    "id": "25",
    "name": "Zamir Narro"
  },
  {
    "id": "26",
    "name": "Humberto Delgado"
  },
  {
    "id": "27",
    "name": "Marcelo Nuñez"
  },
  {
    "id": "28",
    "name": "Mariella Ugarte"
  },
  {
    "id": "29",
    "name": "Marvin Carrasco"
  },
  {
    "id": "30",
    "name": "Nicolle Quispe"
  },
  {
    "id": "31",
    "name": "Orlando Rojas"
  },
  {
    "id": "32",
    "name": "Ricardo Huamani"
  },
  {
    "id": "33",
    "name": "Robert Medina"
  },
  {
    "id": "34",
    "name": "Sebastian Zanabria"
  },
  {
    "id": "36",
    "name": "Victor Rodriguez"
  },
  {
    "id": "37",
    "name": "Wilber Carrascal"
  },
  {
    "id": "38",
    "name": "Andrés Del Carpio"
  },
  {
    "id": "39",
    "name": "Franco Flores"
  }
]
